geode_simplexremeshgeosciences/Geode-SimplexRemeshGeosciences_cross_section.dll
geode_simplexremeshgeosciences/Geode-SimplexRemeshGeosciences_structural_model.dll
geode_simplexremeshgeosciences/__init__.py
geode_simplexremeshgeosciences/cross_section.py
geode_simplexremeshgeosciences/geode_simplexremeshgeosciences_py_cross_section.cp38-win_amd64.pyd
geode_simplexremeshgeosciences/geode_simplexremeshgeosciences_py_structural_model.cp38-win_amd64.pyd
geode_simplexremeshgeosciences/structural_model.py
Geode_SimplexRemeshGeosciences-1.11.2.dist-info/METADATA
Geode_SimplexRemeshGeosciences-1.11.2.dist-info/WHEEL
Geode_SimplexRemeshGeosciences-1.11.2.dist-info/top_level.txt
Geode_SimplexRemeshGeosciences-1.11.2.dist-info/RECORD
