Metadata-Version: 2.1
Name: Geode-SimplexRemeshGeosciences
Version: 1.11.2
Summary: Geosciences simplex remeshing Geode-solutions OpenGeode module
Home-page: https://github.com/Geode-solutions/Geode-SimplexRemeshGeosciences
Author: Geode-solutions
Author-email: contact@geode-solutions.com
License: Proprietary
Requires-Dist: OpenGeode-core (==13.*,>=13.0.0)
Requires-Dist: OpenGeode-Geosciences (==6.*,>=6.0.0)
Requires-Dist: Geode-Common (==24.*,>=24.0.0)
Requires-Dist: Geode-SimplexRemesh (==5.*,>=5.2.0)
